giphycat/__init__.py
giphycat/giphycat.py
giphycat-0.1.dist-info/DESCRIPTION.rst
giphycat-0.1.dist-info/METADATA
giphycat-0.1.dist-info/RECORD
giphycat-0.1.dist-info/WHEEL
giphycat-0.1.dist-info/entry_points.txt
giphycat-0.1.dist-info/metadata.json
giphycat-0.1.dist-info/top_level.txt
