Metadata-Version: 2.0
Name: giphycat
Version: 0.1
Summary: Fetch and display a Giphy image in an iTerm 2 window
Home-page: https://github.com/kstrauser/giphycat
Author: Kirk Strauser
Author-email: kirk@strauser.com
License: MIT
Keywords: giphy iterm iterm2
Platform: UNKNOWN
Requires-Dist: giphypop
Requires-Dist: iterm2-tools
Requires-Dist: requests
